ProgramizJavaJiaochengChuyiFix1/README.md
ProgramizJavaJiaochengChuyiFix1/__init__.py
ProgramizJavaJiaochengChuyiFix1/__main__.py
ProgramizJavaJiaochengChuyiFix1/file.epub
ProgramizJavaJiaochengChuyiFix1/index.html
ProgramizJavaJiaochengChuyiFix1/css/__init__.py
ProgramizJavaJiaochengChuyiFix1/css/annotations.css
ProgramizJavaJiaochengChuyiFix1/css/main.css
ProgramizJavaJiaochengChuyiFix1/css/normalize.css
ProgramizJavaJiaochengChuyiFix1/css/popup.css
ProgramizJavaJiaochengChuyiFix1/font/__init__.py
ProgramizJavaJiaochengChuyiFix1/font/fontello.eot
ProgramizJavaJiaochengChuyiFix1/font/fontello.svg
ProgramizJavaJiaochengChuyiFix1/font/fontello.ttf
ProgramizJavaJiaochengChuyiFix1/font/fontello.woff
ProgramizJavaJiaochengChuyiFix1/img/__init__.py
ProgramizJavaJiaochengChuyiFix1/img/annotator-glyph-sprite.png
ProgramizJavaJiaochengChuyiFix1/img/annotator-icon-sprite.png
ProgramizJavaJiaochengChuyiFix1/img/apple-touch-icon.png
ProgramizJavaJiaochengChuyiFix1/img/cancelfullscreen.png
ProgramizJavaJiaochengChuyiFix1/img/close.png
ProgramizJavaJiaochengChuyiFix1/img/fullscreen.png
ProgramizJavaJiaochengChuyiFix1/img/loader.gif
ProgramizJavaJiaochengChuyiFix1/img/menu-icon.png
ProgramizJavaJiaochengChuyiFix1/img/save.png
ProgramizJavaJiaochengChuyiFix1/img/saved.png
ProgramizJavaJiaochengChuyiFix1/img/settings-s.png
ProgramizJavaJiaochengChuyiFix1/img/settings.png
ProgramizJavaJiaochengChuyiFix1/img/star.png
ProgramizJavaJiaochengChuyiFix1/js/__init__.py
ProgramizJavaJiaochengChuyiFix1/js/epub.js
ProgramizJavaJiaochengChuyiFix1/js/epub.min.js
ProgramizJavaJiaochengChuyiFix1/js/epub.min.map
ProgramizJavaJiaochengChuyiFix1/js/hooks.min.js
ProgramizJavaJiaochengChuyiFix1/js/hooks.min.map
ProgramizJavaJiaochengChuyiFix1/js/reader.js
ProgramizJavaJiaochengChuyiFix1/js/reader.js.map
ProgramizJavaJiaochengChuyiFix1/js/reader.min.js
ProgramizJavaJiaochengChuyiFix1/js/reader.min.map
ProgramizJavaJiaochengChuyiFix1/js/hooks/__init__.py
programiz_java_jiaocheng_chuyi_fix1-2025.3.24.1.dist-info/METADATA
programiz_java_jiaocheng_chuyi_fix1-2025.3.24.1.dist-info/WHEEL
programiz_java_jiaocheng_chuyi_fix1-2025.3.24.1.dist-info/entry_points.txt
programiz_java_jiaocheng_chuyi_fix1-2025.3.24.1.dist-info/top_level.txt
programiz_java_jiaocheng_chuyi_fix1-2025.3.24.1.dist-info/RECORD
